{
  "5b288d4b-4109-4744-8e0e-dd8bc4d2152b": {
    "appActions": [],
    "connectionRef": {
      "apiTier": "Standard",
      "displayName": "SharePoint",
      "iconUri": "https://connectoricons-prod.azureedge.net/releases/v1.0.1685/1.0.1685.3700/sharepointonline/icon.png",
      "id": "/providers/microsoft.powerapps/apis/shared_sharepointonline",
      "parameterHints": {},
      "parameterHintsV2": {}
    },
    "datasets": {
      "https://consusaludsas.sharepoint.com/sites/Operaciones": {
        "dataSources": {
          "Inspección puesto de trabajo video Terminales": {
            "tableName": "e0cd8c0a-3df5-4ad3-96f3-bcc4b70d7c24"
          }
        }
      }
    },
    "dataSources": [
      "Inspección puesto de trabajo video Terminales"
    ],
    "dependencies": {},
    "dependents": [],
    "id": "5b288d4b-4109-4744-8e0e-dd8bc4d2152b"
  },
  "82d7059d-0e80-41e7-88aa-5f2e5d68c100": {
    "appActions": [
      "providers/PowerPlatform.Governance/Operations/Read",
      "providers/PowerPlatform.Governance/Operations/Write"
    ],
    "connectionRef": {
      "apiTier": "Standard",
      "displayName": "SharePoint",
      "iconUri": "https://connectoricons-prod.azureedge.net/releases/v1.0.1685/1.0.1685.3700/sharepointonline/icon.png",
      "id": "/providers/microsoft.powerapps/apis/shared_sharepointonline",
      "parameterHints": {},
      "parameterHintsV2": {}
    },
    "datasets": {
      "https://consusaludsas.sharepoint.com/sites/Operaciones": {
        "dataSources": {
          "Inspección de puesto de trabajo (Operativo)_1": {
            "tableName": "1bab79cc-56c5-4c6f-abf1-4ed1c6e91c77"
          },
          "Inspección de puesto de trabajo (Operativo)_2": {
            "tableName": "1bab79cc-56c5-4c6f-abf1-4ed1c6e91c77"
          }
        }
      },
      "https://consusaludsas.sharepoint.com/sites/Operaciones-Programacin": {
        "dataSources": {
          "Base de datos formulario prueba": {
            "tableName": "73d2b4ff-8302-4d4e-b391-961f0869be5c"
          }
        }
      }
    },
    "dataSources": [
      "Base de datos formulario prueba",
      "Inspección de puesto de trabajo (Operativo)_1",
      "Inspección de puesto de trabajo (Operativo)_2"
    ],
    "dependencies": {},
    "dependents": [],
    "id": "82d7059d-0e80-41e7-88aa-5f2e5d68c100"
  },
  "ad85a0d3-d9b5-4696-918a-9ad848da0f59": {
    "appActions": [
      "providers/PowerPlatform.Governance/Operations/Read",
      "providers/PowerPlatform.Governance/Operations/Write"
    ],
    "connectionRef": {
      "apiTier": "Standard",
      "displayName": "SharePoint",
      "iconUri": "https://connectoricons-prod.azureedge.net/releases/v1.0.1685/1.0.1685.3700/sharepointonline/icon.png",
      "id": "/providers/microsoft.powerapps/apis/shared_sharepointonline",
      "parameterHints": {},
      "parameterHintsV2": {}
    },
    "datasets": {
      "https://consusaludsas.sharepoint.com/sites/Operaciones": {
        "dataSources": {
          "Inspección de puesto de trabajo (Operativo)": {
            "tableName": "1bab79cc-56c5-4c6f-abf1-4ed1c6e91c77"
          },
          "Inspección puesto de trabajo video Terminales_1": {
            "tableName": "e0cd8c0a-3df5-4ad3-96f3-bcc4b70d7c24"
          }
        }
      }
    },
    "dataSources": [
      "Inspección de puesto de trabajo (Operativo)",
      "Inspección puesto de trabajo video Terminales_1"
    ],
    "dependencies": {},
    "dependents": [],
    "id": "ad85a0d3-d9b5-4696-918a-9ad848da0f59"
  },
  "fe5d5ac6-83bd-4b32-9ea9-99aa270a9d02": {
    "appActions": [],
    "connectionRef": {
      "apiTier": "Standard",
      "displayName": "Excel Online (Empresas)",
      "iconUri": "https://connectoricons-prod.azureedge.net/releases/v1.0.1686/1.0.1686.3706/excelonlinebusiness/icon.png",
      "id": "/providers/microsoft.powerapps/apis/shared_excelonlinebusiness",
      "parameterHints": {},
      "parameterHintsV2": {}
    },
    "datasets": {
      "me,b%2521sT2yyQKkIECtFFM0GnmiPvEuABGOcwNDvMrlC7Fr5hp9f5AOJwomRaOmCEV9V4cV,013XVZIPMPGOIXCW2JUZH2N5Y4LUF53NHR": {
        "dataSources": {
          "Tabla1": {
            "tableName": "{0BB5F2B2-A96F-440D-8B04-3A005B9E03F2}"
          }
        }
      },
      "me,b%2521sT2yyQKkIECtFFM0GnmiPvEuABGOcwNDvMrlC7Fr5hp9f5AOJwomRaOmCEV9V4cV,013XVZIPNZJLND54M25JAJPFO2KET6OJEQ": {
        "dataSources": {
          "Tabla3": {
            "tableName": "{5AD9C63D-C5AC-4D16-B3DB-EEDBC02E7AD9}"
          }
        }
      }
    },
    "dataSources": [
      "Tabla1",
      "Tabla3"
    ],
    "dependencies": {},
    "dependents": [],
    "id": "fe5d5ac6-83bd-4b32-9ea9-99aa270a9d02"
  }
}